{
  "weights": {
    "extend_from_atari": 2.992809528653705,
    "connect_vs_peep": 2.483036258967957,
    "block_the_thrust": 1.9968145670973392,
    "hane_vs_tsuke": 1.5595496550729164,
    "hane_at_head_of_two": 1.4671865903155392,
    "stretch_from_kosumi": 1.1955222720352554,
    "block_the_angle": 1.204365612941111,
    "stretch_from_bump": 1.0007155149161753
  },
  "initial_weights": {
    "extend_from_atari": 3.0,
    "connect_vs_peep": 2.5,
    "block_the_thrust": 2.0,
    "hane_vs_tsuke": 1.5,
    "hane_at_head_of_two": 1.5,
    "stretch_from_kosumi": 1.2,
    "block_the_angle": 1.2,
    "stretch_from_bump": 1.0
  },
  "stats": {
    "extend_from_atari": {
      "fired": 36985,
      "followed": 1799,
      "followed_won": 924,
      "followed_lost": 875,
      "ignored_won": 16243,
      "ignored_lost": 18943
    },
    "connect_vs_peep": {
      "fired": 54683,
      "followed": 5060,
      "followed_won": 2648,
      "followed_lost": 2412,
      "ignored_won": 24617,
      "ignored_lost": 25006
    },
    "block_the_thrust": {
      "fired": 38171,
      "followed": 2094,
      "followed_won": 1118,
      "followed_lost": 976,
      "ignored_won": 17920,
      "ignored_lost": 18157
    },
    "hane_vs_tsuke": {
      "fired": 75201,
      "followed": 9633,
      "followed_won": 5776,
      "followed_lost": 3857,
      "ignored_won": 31351,
      "ignored_lost": 34217
    },
    "hane_at_head_of_two": {
      "fired": 68468,
      "followed": 7468,
      "followed_won": 3623,
      "followed_lost": 3845,
      "ignored_won": 30144,
      "ignored_lost": 30856
    },
    "stretch_from_kosumi": {
      "fired": 76397,
      "followed": 19706,
      "followed_won": 10009,
      "followed_lost": 9697,
      "ignored_won": 27636,
      "ignored_lost": 29055
    },
    "block_the_angle": {
      "fired": 76785,
      "followed": 16465,
      "followed_won": 8566,
      "followed_lost": 7899,
      "ignored_won": 29246,
      "ignored_lost": 31074
    },
    "stretch_from_bump": {
      "fired": 39619,
      "followed": 2262,
      "followed_won": 1162,
      "followed_lost": 1100,
      "ignored_won": 18412,
      "ignored_lost": 18945
    }
  },
  "num_games": 2000,
  "win_rates": {
    "extend_from_atari": {
      "fired": 36985,
      "followed": 1799,
      "follow_rate": 0.048641341084223334,
      "follow_winrate": 0.5136186770428015,
      "ignore_winrate": 0.46163246745864833,
      "follow_advantage": 0.051986209584153176
    },
    "connect_vs_peep": {
      "fired": 54683,
      "followed": 5060,
      "follow_rate": 0.09253332845674159,
      "follow_winrate": 0.5233201581027668,
      "ignore_winrate": 0.49608044656711603,
      "follow_advantage": 0.027239711535650746
    },
    "block_the_thrust": {
      "fired": 38171,
      "followed": 2094,
      "follow_rate": 0.05485840035629143,
      "follow_winrate": 0.5339063992359121,
      "ignore_winrate": 0.49671535881586604,
      "follow_advantage": 0.03719104042004606
    },
    "hane_vs_tsuke": {
      "fired": 75201,
      "followed": 9633,
      "follow_rate": 0.12809670084174413,
      "follow_winrate": 0.5996055226824457,
      "ignore_winrate": 0.47814482674475356,
      "follow_advantage": 0.12146069593769215
    },
    "hane_at_head_of_two": {
      "fired": 68468,
      "followed": 7468,
      "follow_rate": 0.10907285155108956,
      "follow_winrate": 0.4851365827530798,
      "ignore_winrate": 0.4941639344262295,
      "follow_advantage": -0.00902735167314972
    },
    "stretch_from_kosumi": {
      "fired": 76397,
      "followed": 19706,
      "follow_rate": 0.2579420657879236,
      "follow_winrate": 0.5079163706485335,
      "ignore_winrate": 0.48748478594485894,
      "follow_advantage": 0.02043158470367451
    },
    "block_the_angle": {
      "fired": 76785,
      "followed": 16465,
      "follow_rate": 0.21442990167350395,
      "follow_winrate": 0.5202550865472214,
      "ignore_winrate": 0.4848474801061008,
      "follow_advantage": 0.03540760644112062
    },
    "stretch_from_bump": {
      "fired": 39619,
      "followed": 2262,
      "follow_rate": 0.057093818622378154,
      "follow_winrate": 0.5137046861184792,
      "ignore_winrate": 0.4928661295071874,
      "follow_advantage": 0.020838556611291803
    }
  }
}